Obsidian/__init__.py
Obsidian/cmdline.py
Obsidian/ddsourceconfig.py
Obsidian/ddsourcejsonconfig.py
Obsidian/ddspider.py
Obsidian/items.py
Obsidian/pipelines.py
Obsidian/settings.py
Obsidian/spiders/__init__.py
Obsidian/spiders/jsonspider.py
Obsidian-1.0.1.data/scripts/obsidian.py
Obsidian-1.0.1.dist-info/DESCRIPTION.rst
Obsidian-1.0.1.dist-info/METADATA
Obsidian-1.0.1.dist-info/RECORD
Obsidian-1.0.1.dist-info/WHEEL
Obsidian-1.0.1.dist-info/metadata.json
Obsidian-1.0.1.dist-info/pbr.json
Obsidian-1.0.1.dist-info/top_level.txt
