Metadata-Version: 2.0
Name: Obsidian
Version: 1.0.1
Summary: Obsidian make web crawl easier
Home-page: https://github.com/amoblin/Obsidian
Author: amoblin
Author-email: amoblin@gmail.com
License: MIT
Keywords: web crawl json
Platform: UNKNOWN
Requires-Dist: scrapy
